pyprocessing/__init__.py
pyprocessing/__main__.py
pyprocessing/attributes.py
pyprocessing/calculation.py
pyprocessing/color.py
pyprocessing/constants.py
pyprocessing/converter.py
pyprocessing/environment.py
pyprocessing/image.py
pyprocessing/math.py
pyprocessing/primitives_2d.py
pyprocessing/pyprocessing.py
pyprocessing/random.py
pyprocessing/runner.py
pyprocessing/structure.py
pyprocessing/time.py
pyprocessing/utils.py
pyprocessing/renderer/__init__.py
pyprocessing/renderer/actions.py
pyprocessing/renderer/tkinter/__init__.py
pyprocessing/renderer/tkinter/renderer.py
pyprocessing/renderer/tkinter/window.py
tests/__init__.py
tests/base.py
tests/test_pyprocessing_math.py
pyprocessing2-0.0.1b6.dist-info/AUTHORS.md
pyprocessing2-0.0.1b6.dist-info/LICENSE
pyprocessing2-0.0.1b6.dist-info/METADATA
pyprocessing2-0.0.1b6.dist-info/WHEEL
pyprocessing2-0.0.1b6.dist-info/top_level.txt
pyprocessing2-0.0.1b6.dist-info/RECORD
