Metadata-Version: 2.1
Name: pyprocessing2
Version: 0.0.1b6
Summary: A pure Python version of the Processing language 
Home-page: https://www.github.com/Dogeek/pyprocessing
Author: Dogeek
License: MIT
Download-URL: https://www.github.com/Dogeek/pyprocessing/releases
Platform: UNKNOWN
Classifier: Development Status :: 4 - Beta
Classifier: Intended Audience :: Developers
Classifier: License :: OSI Approved :: MIT License
Classifier: Operating System :: POSIX
Classifier: Operating System :: Microsoft :: Windows
Classifier: Programming Language :: Python :: 3 :: Only
Classifier: Programming Language :: Python :: 3.8
Classifier: Topic :: Software Development :: Libraries
Requires-Python: >=3.8
Requires-Dist: Pillow
Requires-Dist: lxml
Requires-Dist: noise
Requires-Dist: stringcase
Requires-Dist: svgwrite
Requires-Dist: requests
